Metadata-Version: 2.1
Name: html2markdown
Version: 0.1.6.post0
Summary: Conservatively convert html to markdown
Home-page: https://github.com/dlon/html2markdown
Author: David Lönnhager
Author-email: dv.lnh.d@gmail.com
License: UNKNOWN
Platform: UNKNOWN
